LICENSE
dotwarden/__init__.py
dotwarden-1.0.4.dist-info/LICENSE
dotwarden-1.0.4.dist-info/WHEEL
dotwarden-1.0.4.dist-info/METADATA
dotwarden-1.0.4.dist-info/RECORD
