Metadata-Version: 2.1
Name: dotwarden
Version: 1.0.4
Summary: a utility for generating hidden random . directories
Home-page: https://github.com/JaffarA/dotwarden
License: GPLv3
Author: Jaffar
Author-email: jaffar.almaleki@gmail.com
Requires-Python: >=3.4,<4.0
Classifier: License :: Other/Proprietary License
Classifier: Programming Language :: Python :: 3
Classifier: Programming Language :: Python :: 3.10
Classifier: Programming Language :: Python :: 3.4
Classifier: Programming Language :: Python :: 3.5
Classifier: Programming Language :: Python :: 3.6
Classifier: Programming Language :: Python :: 3.7
Classifier: Programming Language :: Python :: 3.8
Classifier: Programming Language :: Python :: 3.9
Project-URL: Repository, https://github.com/JaffarA/dotwarden
